radiometry/__init__.py
radiometry/dataset.py
radiometry/metadata.py
radiometry/__pycache__/__init__.cpython-39.pyc
radiometry/__pycache__/dataset.cpython-39.pyc
radiometry/__pycache__/metadata.cpython-39.pyc
radiometry-0.1.0.dev15.dist-info/COPYING
radiometry-0.1.0.dev15.dist-info/LICENSE
radiometry-0.1.0.dev15.dist-info/METADATA
radiometry-0.1.0.dev15.dist-info/WHEEL
radiometry-0.1.0.dev15.dist-info/top_level.txt
radiometry-0.1.0.dev15.dist-info/RECORD
