Metadata-Version: 2.2
Name: radiometry
Version: 0.1.0.dev15
Summary: Reproducible and automated processing and analysis of (synchrotron) radiometry data based on the ASpecD framework
Home-page: https://www.radiometry.de/
Author: Till Biskup
Author-email: code@till-biskup.de
License: GPLv3
Project-URL: Documentation, https://docs.radiometry.de/
Project-URL: Source, https://github.com/tillbiskup/radiometry
Keywords: eve,radiometry,synchrotron,metrology,PTB,MLS,BESSY,data processing and analysis,reproducible science,reproducible research,good scientific practice,recipe-driven data analysis
Classifier: Programming Language :: Python :: 3
Classifier: Programming Language :: Python :: 3.9
Classifier: Programming Language :: Python :: 3.10
Classifier: Programming Language :: Python :: 3.11
Classifier: Programming Language :: Python :: 3.12
Classifier: License :: OSI Approved :: GNU General Public License v3 (GPLv3)
Classifier: Operating System :: OS Independent
Classifier: Intended Audience :: Science/Research
Classifier: Development Status :: 4 - Beta
Requires-Python: >=3.9
License-File: LICENSE
License-File: COPYING
Requires-Dist: aspecd
Requires-Dist: h5py
Provides-Extra: dev
Requires-Dist: prospector; extra == "dev"
Requires-Dist: pyroma; extra == "dev"
Requires-Dist: bandit; extra == "dev"
Requires-Dist: black; extra == "dev"
Requires-Dist: pymetacode; extra == "dev"
Provides-Extra: docs
Requires-Dist: sphinx; extra == "docs"
Requires-Dist: sphinx-rtd-theme; extra == "docs"
Requires-Dist: sphinx_multiversion; extra == "docs"
Provides-Extra: deployment
Requires-Dist: build; extra == "deployment"
Requires-Dist: twine; extra == "deployment"
Dynamic: author
Dynamic: author-email
Dynamic: classifier
Dynamic: description
Dynamic: description-content-type
Dynamic: home-page
Dynamic: keywords
Dynamic: license
Dynamic: project-url
Dynamic: provides-extra
Dynamic: requires-dist
Dynamic: requires-python
Dynamic: summary
